surveyequivalence/__init__.py
surveyequivalence/combiners.py
surveyequivalence/data_noise_generator.py
surveyequivalence/equivalence.py
surveyequivalence/scoring_functions.py
surveyequivalence/synthetic_datasets.py
surveyequivalence/data/credweb.csv
surveyequivalence/data/vote_gtk2.csv
surveyequivalence/data/wiki_attack_labels_and_predictor.csv
surveyequivalence/data/running_example/predictions.csv
surveyequivalence/data/running_example/ref_rater_labels.csv
surveyequivalence/data/running_example_50_items/predictions.csv
surveyequivalence/data/running_example_50_items/ref_rater_labels.csv
surveyequivalence/examples/__init__.py
surveyequivalence/examples/credbank.py
surveyequivalence/examples/guessthekarma.py
surveyequivalence/examples/paper_running_example.py
surveyequivalence/examples/personal_attacks.py
surveyequivalence/templates/classifier_template.txt
surveyequivalence/templates/performance_ratio_template.txt
surveyequivalence/templates/pgf_template.txt
surveyequivalence/templates/plot_template.txt
surveyequivalence/templates/surveyequiv_template.txt
surveyequivalence-0.1.3.dist-info/LICENSE
surveyequivalence-0.1.3.dist-info/METADATA
surveyequivalence-0.1.3.dist-info/WHEEL
surveyequivalence-0.1.3.dist-info/top_level.txt
surveyequivalence-0.1.3.dist-info/RECORD
