Metadata-Version: 2.1
Name: surveyequivalence
Version: 0.1.3
Summary: Code for calculating survey equivalence
Home-page: https://github.com/presnick/surveyequivalence
Author: Paul Resnick, Tim Weninger, Yuqing Kong, and Grant Schoenebeck
Author-email: presnick@umich.edu
Project-URL: Bug Tracker, https://github.com/presnick/surveyequivalence/issues
Classifier: Programming Language :: Python :: 3
Classifier: License :: OSI Approved :: MIT License
Classifier: Operating System :: OS Independent
Requires-Python: >=3.8
License-File: LICENSE
Requires-Dist: setuptools (~=67.6.1)
Requires-Dist: numpy (~=1.24.0)
Requires-Dist: pandas (~=2.0.0)
Requires-Dist: matplotlib (~=3.7.1)
Requires-Dist: scikit-learn (~=1.2.2)
Requires-Dist: multipledispatch (~=0.6.0)
Requires-Dist: multiprocess (~=0.70.14)
Requires-Dist: statsmodels (~=0.13.5)
Requires-Dist: pathos (~=0.3.0)
